LUT_openSTA/Lut.v
module Lut (
    input [4:0] a,
    input [4:0] b,
    input clk,
    input reset,
    input [1:0] s,
    input sync,
    output reg [4:0] out
);

reg [4:0] y;

always @(*) begin
    y = 5'b0;
    case (s)
        2'b00: y = a & b;
        2'b01: y = a | b;
        2'b10: y = a + b;
        2'b11: y = a - b;
    endcase
end

always @(posedge clk) begin
    if (reset)
        out <= 5'b0;
    else if (sync)
        out <= y;
end

endmodule

LUT_openSTA/Lut_tb.v
`timescale 1ns/1ps

module Lut_tb;

reg [4:0] a;
reg [4:0] b;
reg clk;
reg reset;
reg [1:0] s;
reg sync;
wire [4:0] out;

// DUT
Lut uut (
    .a(a),
    .b(b),
    .clk(clk),
    .reset(reset),
    .s(s),
    .sync(sync),
    .out(out)
);

// Clock (10ns period)
always #5 clk = ~clk;

// waveform
initial begin
    $dumpfile("wave.vcd");
    $dumpvars(0, Lut_tb);
end

// stimulus
initial begin
    clk = 0;
    reset = 1;
    sync = 0;
    a = 0;
    b = 0;
    s = 0;

    // ---- Reset phase ----
    repeat (2) @(posedge clk);
    reset <= 0;

    // ---- AND ----
    @(negedge clk);
    a <= 5'b10101;
    b <= 5'b11000;
    s <= 2'b00;
    sync <= 1;

    @(posedge clk);

    // ---- OR ----
    @(negedge clk);
    s <= 2'b01;

    @(posedge clk);

    // ---- ADD ----
    @(negedge clk);
    a <= 5'd10;
    b <= 5'd5;
    s <= 2'b10;

    @(posedge clk);

    // ---- SUB ----
    @(negedge clk);
    a <= 5'd15;
    b <= 5'd3;
    s <= 2'b11;

    @(posedge clk);

    // ---- async mode off ----
    @(negedge clk);
    sync <= 0;
    a <= 5'b11111;
    b <= 5'b00001;
    s <= 2'b00;

    @(posedge clk);

    $finish;
end

// monitor
initial begin
    $monitor("Time=%0t | a=%b b=%b s=%b sync=%b out=%b",
             $time, a, b, s, sync, out);
end

endmodule

LUT_openSTA/wave.vcd
$date
	Tue Apr 14 16:43:51 2026
$end
$version
	Icarus Verilog
$end
$timescale
	1ps
$end
$scope module Lut_tb $end
$var wire 5 ! out [4:0] $end
$var reg 5 " a [4:0] $end
$var reg 5 # b [4:0] $end
$var reg 1 $ clk $end
$var reg 1 % reset $end
$var reg 2 & s [1:0] $end
$var reg 1 ' sync $end
$scope module uut $end
$var wire 5 ( a [4:0] $end
$var wire 5 ) b [4:0] $end
$var wire 1 $ clk $end
$var wire 1 % reset $end
$var wire 2 * s [1:0] $end
$var wire 1 ' sync $end
$var reg 5 + out [4:0] $end
$var reg 5 , y [4:0] $end
$upscope $end
$upscope $end
$enddefinitions $end
$comment Show the parameter values. $end
$dumpall
$end
#0
$dumpvars
b0 ,
bx +
b0 *
b0 )
b0 (
0'
b0 &
1%
0$
b0 #
b0 "
bx !
$end
#5000
b0 !
b0 +
1$
#10000
0$
#15000
0%
1$
#20000
b10000 ,
1'
b11000 #
b11000 )
b10101 "
b10101 (
0$
#25000
b10000 !
b10000 +
1$
#30000
b11101 ,
b1 &
b1 *
0$
#35000
b11101 !
b11101 +
1$
#40000
b1111 ,
b10 &
b10 *
b101 #
b101 )
b1010 "
b1010 (
0$
#45000
b1111 !
b1111 +
1$
#50000
b1100 ,
b11 &
b11 *
b11 #
b11 )
b1111 "
b1111 (
0$
#55000
b1100 !
b1100 +
1$
#60000
b1 ,
b0 &
b0 *
b1 #
b1 )
b11111 "
b11111 (
0'
0$
